interface_script/__init__.py
interface_script/parser.py
interface_script-1.1.dist-info/LICENSE.txt
interface_script-1.1.dist-info/METADATA
interface_script-1.1.dist-info/WHEEL
interface_script-1.1.dist-info/top_level.txt
interface_script-1.1.dist-info/RECORD
