Metadata-Version: 2.1
Name: interface-script
Version: 1.1
Summary: Message-oriented data-interchange format
Home-page: https://github.com/cratuki/interface_script_py
Author: Craig Turner
Author-email: cratuki@gmail.com
License: MIT
Download-URL: https://github.com/cratuki/interface_script_py/archive/v1.1.tar.gz
Keywords: interchange,textual,message-driven,event-driven
Platform: UNKNOWN
Classifier: Development Status :: 5 - Production/Stable
Classifier: Intended Audience :: Developers
Classifier: Topic :: Software Development :: Build Tools
Classifier: License :: OSI Approved :: MIT License
Classifier: Programming Language :: Python :: 3.3
Classifier: Programming Language :: Python :: 3.4
Classifier: Programming Language :: Python :: 3.5
Classifier: Programming Language :: Python :: 3.6
Classifier: Programming Language :: Python :: 3.7
Classifier: Programming Language :: Python :: 3.8
Classifier: Programming Language :: Python :: 3.9
